MANIFEST.in
README.md
setup.py
docs/conf.py
docs/tutorial/__init__.py
docs/tutorial/todomanager.py
docs/tutorial/tutorial1.py
pycommunicate/__init__.py
pycommunicate/templating.py
pycommunicate/util.py
pycommunicate.egg-info/PKG-INFO
pycommunicate.egg-info/SOURCES.txt
pycommunicate.egg-info/dependency_links.txt
pycommunicate.egg-info/not-zip-safe
pycommunicate.egg-info/requires.txt
pycommunicate.egg-info/top_level.txt
pycommunicate/proxies/__init__.py
pycommunicate/proxies/context.py
pycommunicate/proxies/socket.py
pycommunicate/proxies/dom/__init__.py
pycommunicate/proxies/dom/element.py
pycommunicate/proxies/dom/html.py
pycommunicate/proxies/dom/property.py
pycommunicate/server/__init__.py
pycommunicate/server/app/__init__.py
pycommunicate/server/app/communicate.py
pycommunicate/server/app/socketio.py
pycommunicate/server/app/usertrack.py
pycommunicate/server/bases/__init__.py
pycommunicate/server/bases/controller.py
pycommunicate/server/bases/views.py
pycommunicate/templates/__pycommunicate_html/includes.html
pycommunicate/templates/__pycommunicate_js/pycommunicate.js