Metadata-Version: 1.1
Name: pycommunicate
Version: 0.0.7
Summary: A web library focusing on handling JS events server-side
Home-page: https://github.com/mincrmatt12/pycommunicate
Author: mincrmatt12
Author-email: nope@nope.com
License: MIT
Platform: UNKNOWN
Classifier: Development Status :: 2 - Pre-Alpha
Classifier: License :: OSI Approved :: MIT License
Classifier: Programming Language :: Python :: 2.7
Classifier: Programming Language :: Python :: 2 :: Only
Classifier: Topic :: Internet :: WWW/HTTP :: Dynamic Content
Classifier: Operating System :: OS Independent
Classifier: Intended Audience :: Developers
